{"v":"5.5.6","fr":25,"ip":0,"op":25,"w":62,"h":62,"nm":"竞拍","ddd":0,"assets":[{"id":"comp_0","layers":[{"ddd":0,"ind":1,"ty":4,"nm":"形状图层 14","sr":1,"ks":{"o":{"a":0,"k":100,"ix":11},"r":{"a":0,"k":0,"ix":10},"p":{"a":0,"k":[31,31,0],"ix":2},"a":{"a":0,"k":[0,0,0],"ix":1},"s":{"a":0,"k":[100,100,100],"ix":6}},"ao":0,"shapes":[{"ty":"gr","it":[{"ind":0,"ty":"sh","ix":1,"ks":{"a":0,"k":{"i":[[2.375,2.188],[0,0],[2.188,-2.312],[0,0],[-2.062,-1.875],[0,0],[-1.562,1.438],[0,0],[-1.755,-1.682],[0,0],[-1.312,1.438],[0,0],[1.375,1.5],[0,0],[-1.971,1.971],[0,0]],"o":[[-2.795,-2.575],[0,0],[-2.188,2.312],[0,0],[2.062,1.875],[0,0],[1.953,-1.796],[0,0],[1.5,1.438],[0,0],[1.205,-1.32],[0,0],[-1.375,-1.5],[0,0],[2.812,-2.813],[0,0]],"v":[[5.438,-21.688],[0.125,-21.75],[-16.25,-5.5],[-16.5,-0.5],[-10.562,5.688],[-5.938,5.812],[-2.062,2.187],[1.188,2.375],[12.625,14.125],[15.875,14.75],[19.875,11.062],[20.125,7.875],[7.438,-4.75],[7.438,-7.625],[10.875,-11.062],[11.062,-16.312]],"c":true},"ix":2},"nm":"路径 1","mn":"ADBE Vector Shape - Group","hd":false},{"ty":"gf","o":{"a":0,"k":100,"ix":10},"r":1,"bm":0,"g":{"p":3,"k":{"a":0,"k":[0,1,0.22,0.443,0.5,1,0.11,0.345,1,1,0,0.247],"ix":9}},"s":{"a":0,"k":[-17.092,-22.953],"ix":5},"e":{"a":0,"k":[20.559,14.955],"ix":6},"t":1,"nm":"Gradient Fill 1","mn":"ADBE Vector Graphic - G-Fill","hd":false},{"ty":"tr","p":{"a":0,"k":[0,0],"ix":2},"a":{"a":0,"k":[0,0],"ix":1},"s":{"a":0,"k":[100,100],"ix":3},"r":{"a":0,"k":0,"ix":6},"o":{"a":0,"k":100,"ix":7},"sk":{"a":0,"k":0,"ix":4},"sa":{"a":0,"k":0,"ix":5},"nm":"变换"}],"nm":"形状 1","np":3,"cix":2,"bm":0,"ix":1,"mn":"ADBE Vector Group","hd":false}],"ip":0,"op":75,"st":0,"bm":0},{"ddd":0,"ind":2,"ty":4,"nm":"形状图层 15","sr":1,"ks":{"o":{"a":0,"k":100,"ix":11},"r":{"a":0,"k":0,"ix":10},"p":{"a":0,"k":[31,31,0],"ix":2},"a":{"a":0,"k":[0,0,0],"ix":1},"s":{"a":0,"k":[100,100,100],"ix":6}},"ao":0,"shapes":[{"ty":"gr","it":[{"ty":"rc","d":1,"s":{"a":0,"k":[24,3],"ix":2},"p":{"a":0,"k":[0,0],"ix":3},"r":{"a":0,"k":532,"ix":4},"nm":"矩形路径 1","mn":"ADBE Vector Shape - Rect","hd":false},{"ty":"gf","o":{"a":0,"k":100,"ix":10},"r":1,"bm":0,"g":{"p":3,"k":{"a":0,"k":[0,1,0.22,0.443,0.5,1,0.11,0.345,1,1,0,0.247],"ix":9}},"s":{"a":0,"k":[-3.325,-22.449],"ix":5},"e":{"a":0,"k":[19.664,-0.34],"ix":6},"t":1,"nm":"Gradient Fill 1","mn":"ADBE Vector Graphic - G-Fill","hd":false},{"ty":"tr","p":{"a":0,"k":[-5.004,15.481],"ix":2},"a":{"a":0,"k":[0,0],"ix":1},"s":{"a":0,"k":[100,100],"ix":3},"r":{"a":0,"k":0,"ix":6},"o":{"a":0,"k":100,"ix":7},"sk":{"a":0,"k":0,"ix":4},"sa":{"a":0,"k":0,"ix":5},"nm":"变换"}],"nm":"矩形 1","np":3,"cix":2,"bm":0,"ix":1,"mn":"ADBE Vector Group","hd":false}],"ip":0,"op":75,"st":0,"bm":0}]}],"layers":[{"ddd":0,"ind":1,"ty":4,"nm":"形状图层 12","sr":1,"ks":{"o":{"a":1,"k":[{"i":{"x":[0.667],"y":[1]},"o":{"x":[0.333],"y":[0]},"t":5,"s":[100]},{"t":9,"s":[0]}],"ix":11},"r":{"a":0,"k":0,"ix":10},"p":{"a":0,"k":[31,31,0],"ix":2},"a":{"a":0,"k":[0,0,0],"ix":1},"s":{"a":0,"k":[100,100,100],"ix":6}},"ao":0,"shapes":[{"ty":"gr","it":[{"ind":0,"ty":"sh","ix":1,"ks":{"a":0,"k":{"i":[[2.25,2.25],[0,0],[2.188,-2.312],[0,0],[-2.062,-1.875],[0,0],[-1.812,1.938],[0,0],[-1.672,-1.765],[-0.938,0.812],[-1.16,1.36],[0,0],[1.375,1.5],[0,0],[-2.062,1.875],[0,0]],"o":[[-2.25,-2.25],[0,0],[-2.188,2.312],[0,0],[2.062,1.875],[0,0],[1.812,-1.938],[0,0],[1.406,1.406],[0.625,-0.625],[1.625,-1.906],[0,0],[-1.375,-1.5],[0,0],[2.062,-1.875],[0,0]],"v":[[5.312,-20.625],[0.5,-20.188],[-14.688,-5.188],[-15.312,-0.875],[-10.438,4.438],[-6.375,4.562],[-2.75,1.188],[1.062,1],[12.625,12.5],[16.125,13.375],[18.438,10.875],[18.625,7.375],[6,-4.812],[6,-7.688],[9.812,-11.562],[10.312,-15.25]],"c":true},"ix":2},"nm":"路径 1","mn":"ADBE Vector Shape - Group","hd":false},{"ty":"st","c":{"a":0,"k":[0.16862745098,0.180392156863,0.203921568627,1],"ix":3},"o":{"a":0,"k":100,"ix":4},"w":{"a":0,"k":3,"ix":5},"lc":2,"lj":2,"bm":0,"nm":"描边 1","mn":"ADBE Vector Graphic - Stroke","hd":false},{"ty":"tr","p":{"a":0,"k":[0,0],"ix":2},"a":{"a":0,"k":[0,0],"ix":1},"s":{"a":0,"k":[100,100],"ix":3},"r":{"a":0,"k":0,"ix":6},"o":{"a":0,"k":100,"ix":7},"sk":{"a":0,"k":0,"ix":4},"sa":{"a":0,"k":0,"ix":5},"nm":"变换"}],"nm":"形状 1","np":3,"cix":2,"bm":0,"ix":1,"mn":"ADBE Vector Group","hd":false},{"ty":"tm","s":{"a":0,"k":0,"ix":1},"e":{"a":1,"k":[{"i":{"x":[0.667],"y":[1]},"o":{"x":[0.333],"y":[0]},"t":0,"s":[100]},{"t":10,"s":[0]}],"ix":2},"o":{"a":0,"k":180,"ix":3},"m":1,"ix":2,"nm":"修剪路径 1","mn":"ADBE Vector Filter - Trim","hd":false}],"ip":0,"op":75,"st":0,"bm":0},{"ddd":0,"ind":2,"ty":4,"nm":"形状图层 13","sr":1,"ks":{"o":{"a":1,"k":[{"i":{"x":[0.667],"y":[1]},"o":{"x":[0.333],"y":[0]},"t":5,"s":[100]},{"t":8,"s":[0]}],"ix":11},"r":{"a":0,"k":0,"ix":10},"p":{"a":0,"k":[31,31,0],"ix":2},"a":{"a":0,"k":[0,0,0],"ix":1},"s":{"a":0,"k":[100,100,100],"ix":6}},"ao":0,"shapes":[{"ty":"gr","it":[{"ind":0,"ty":"sh","ix":1,"ks":{"a":0,"k":{"i":[[0,0],[0,0]],"o":[[0,0],[0,0]],"v":[[-15.188,15.5],[5.125,15.5]],"c":false},"ix":2},"nm":"路径 1","mn":"ADBE Vector Shape - Group","hd":false},{"ty":"st","c":{"a":0,"k":[0.16862745098,0.180392156863,0.203921568627,1],"ix":3},"o":{"a":0,"k":100,"ix":4},"w":{"a":0,"k":3,"ix":5},"lc":2,"lj":2,"bm":0,"nm":"描边 1","mn":"ADBE Vector Graphic - Stroke","hd":false},{"ty":"tr","p":{"a":0,"k":[0,0],"ix":2},"a":{"a":0,"k":[0,0],"ix":1},"s":{"a":0,"k":[100,100],"ix":3},"r":{"a":0,"k":0,"ix":6},"o":{"a":0,"k":100,"ix":7},"sk":{"a":0,"k":0,"ix":4},"sa":{"a":0,"k":0,"ix":5},"nm":"变换"}],"nm":"形状 1","np":3,"cix":2,"bm":0,"ix":1,"mn":"ADBE Vector Group","hd":false},{"ty":"tm","s":{"a":0,"k":0,"ix":1},"e":{"a":1,"k":[{"i":{"x":[0.667],"y":[1]},"o":{"x":[0.333],"y":[0]},"t":0,"s":[100]},{"t":8,"s":[0]}],"ix":2},"o":{"a":0,"k":0,"ix":3},"m":1,"ix":2,"nm":"修剪路径 1","mn":"ADBE Vector Filter - Trim","hd":false}],"ip":0,"op":75,"st":0,"bm":0},{"ddd":0,"ind":3,"ty":0,"nm":"点亮","refId":"comp_0","sr":1,"ks":{"o":{"a":1,"k":[{"i":{"x":[0.667],"y":[1]},"o":{"x":[0.333],"y":[0]},"t":3,"s":[0]},{"t":9.8623046875,"s":[100]}],"ix":11},"r":{"a":0,"k":0,"ix":10},"p":{"a":0,"k":[31,31,0],"ix":2},"a":{"a":0,"k":[31,31,0],"ix":1},"s":{"a":1,"k":[{"i":{"x":[0.667,0.667,0.667],"y":[1,1,1]},"o":{"x":[0.333,0.333,0.333],"y":[0,0,0]},"t":3.862,"s":[70,70,100]},{"i":{"x":[0.667,0.667,0.667],"y":[1,1,1]},"o":{"x":[0.333,0.333,0.333],"y":[0,0,0]},"t":4.862,"s":[62.963,63.187,100]},{"i":{"x":[0.667,0.667,0.667],"y":[1,1,1]},"o":{"x":[0.333,0.333,0.333],"y":[0,0,0]},"t":5.862,"s":[70.37,71.153,100]},{"i":{"x":[0.667,0.667,0.667],"y":[1,1,1]},"o":{"x":[0.333,0.333,0.333],"y":[0,0,0]},"t":7.862,"s":[89.63,91.866,100]},{"i":{"x":[0.667,0.667,0.667],"y":[1,1,1]},"o":{"x":[0.333,0.333,0.333],"y":[0,0,0]},"t":8.862,"s":[97.037,99.833,100]},{"i":{"x":[0.667,0.667,0.667],"y":[1,1,1]},"o":{"x":[0.333,0.333,0.333],"y":[0,0,0]},"t":9.862,"s":[100,100,100]},{"i":{"x":[0.667,0.667,0.667],"y":[1,1,1]},"o":{"x":[0.333,0.333,0.333],"y":[0,0,0]},"t":10.862,"s":[103.791,107.097,100]},{"i":{"x":[0.667,0.667,0.667],"y":[1,1,1]},"o":{"x":[0.333,0.333,0.333],"y":[0,0,0]},"t":11.862,"s":[104.71,108.085,100]},{"i":{"x":[0.667,0.667,0.667],"y":[1,1,1]},"o":{"x":[0.333,0.333,0.333],"y":[0,0,0]},"t":12.862,"s":[103.099,106.352,100]},{"i":{"x":[0.667,0.667,0.667],"y":[1,1,1]},"o":{"x":[0.333,0.333,0.333],"y":[0,0,0]},"t":13.862,"s":[100.429,103.482,100]},{"i":{"x":[0.667,0.667,0.667],"y":[1,1,1]},"o":{"x":[0.333,0.333,0.333],"y":[0,0,0]},"t":14.862,"s":[98.284,101.174,100]},{"i":{"x":[0.667,0.667,0.667],"y":[1,1,1]},"o":{"x":[0.333,0.333,0.333],"y":[0,0,0]},"t":15.862,"s":[97.556,100.391,100]},{"i":{"x":[0.667,0.667,0.667],"y":[1,1,1]},"o":{"x":[0.333,0.333,0.333],"y":[0,0,0]},"t":16.862,"s":[98.21,101.094,100]},{"i":{"x":[0.667,0.667,0.667],"y":[1,1,1]},"o":{"x":[0.333,0.333,0.333],"y":[0,0,0]},"t":17.862,"s":[99.551,102.536,100]},{"i":{"x":[0.667,0.667,0.667],"y":[1,1,1]},"o":{"x":[0.333,0.333,0.333],"y":[0,0,0]},"t":18.862,"s":[100.742,103.818,100]},{"i":{"x":[0.667,0.667,0.667],"y":[1,1,1]},"o":{"x":[0.333,0.333,0.333],"y":[0,0,0]},"t":19.862,"s":[101.248,104.362,100]},{"i":{"x":[0.667,0.667,0.667],"y":[1,1,1]},"o":{"x":[0.333,0.333,0.333],"y":[0,0,0]},"t":20.862,"s":[101.012,104.108,100]},{"i":{"x":[0.667,0.667,0.667],"y":[1,1,1]},"o":{"x":[0.333,0.333,0.333],"y":[0,0,0]},"t":21.862,"s":[100.351,103.397,100]},{"i":{"x":[0.667,0.667,0.667],"y":[1,1,1]},"o":{"x":[0.333,0.333,0.333],"y":[0,0,0]},"t":22.862,"s":[99.701,102.698,100]},{"t":23.8623046875,"s":[100,100,100]}],"ix":6}},"ao":0,"w":62,"h":62,"ip":0,"op":100,"st":0,"bm":0}],"markers":[]}