{"v":"4.8.0","meta":{"g":"LottieFiles AE ","a":"","k":"","d":"","tc":""},"fr":60,"ip":0,"op":120,"w":200,"h":200,"nm":"connect","ddd":0,"assets":[],"layers":[{"ddd":0,"ind":1,"ty":4,"nm":"connect-female Outlines","sr":1,"ks":{"o":{"a":0,"k":100,"ix":11},"r":{"a":0,"k":0,"ix":10},"p":{"a":1,"k":[{"i":{"x":0.108,"y":1},"o":{"x":0.558,"y":0},"t":0,"s":[120.477,79.408,0],"to":[-0.323,0.323,0],"ti":[0.844,-0.844,0]},{"i":{"x":0.047,"y":1},"o":{"x":0.4,"y":0},"t":30,"s":[113.477,86.408,0],"to":[-1.167,1.167,0],"ti":[1.167,-1.167,0]},{"i":{"x":0.842,"y":0.848},"o":{"x":0.558,"y":0},"t":60,"s":[125.477,74.408,0],"to":[-0.323,0.323,0],"ti":[0.71,-0.71,0]},{"i":{"x":0.667,"y":1},"o":{"x":0.443,"y":0.773},"t":79.666,"s":[118.854,81.03,0],"to":[-1.857,1.857,0],"ti":[1.167,-1.167,0]},{"t":119,"s":[125.477,74.408,0]}],"ix":2},"a":{"a":0,"k":[23.485,23.485,0],"ix":1},"s":{"a":0,"k":[100,100,100],"ix":6}},"ao":0,"shapes":[{"ty":"gr","it":[{"ind":0,"ty":"sh","ix":1,"ks":{"a":0,"k":{"i":[[3.559,5.781],[-0.051,0.051],[0,0],[1.367,1.367],[1.367,-1.367],[0,0],[0.047,-0.053],[5.01,-5.01],[0,0],[0,0],[0,0]],"o":[[0.053,-0.047],[0,0],[1.367,-1.367],[-1.367,-1.367],[0,0],[-0.051,0.051],[-5.78,-3.559],[0,0],[0,0],[0,0],[5.01,-5.01]],"v":[[11.807,-6.887],[11.969,-7.02],[21.868,-16.919],[21.868,-21.868],[16.919,-21.868],[7.02,-11.969],[6.887,-11.807],[-11.568,-9.645],[-23.236,2.023],[-2.023,23.236],[9.645,11.568]],"c":true},"ix":2},"nm":"Path 1","mn":"ADBE Vector Shape - Group","hd":false},{"ty":"tr","p":{"a":0,"k":[23.485,23.486],"ix":2},"a":{"a":0,"k":[0,0],"ix":1},"s":{"a":0,"k":[100,100],"ix":3},"r":{"a":0,"k":0,"ix":6},"o":{"a":0,"k":100,"ix":7},"sk":{"a":0,"k":0,"ix":4},"sa":{"a":0,"k":0,"ix":5},"nm":"Transform"}],"nm":"Group 1","np":1,"cix":2,"bm":0,"ix":1,"mn":"ADBE Vector Group","hd":false},{"ty":"fl","c":{"a":0,"k":[1,1,1,1],"ix":4},"o":{"a":1,"k":[{"i":{"x":[0.667],"y":[1]},"o":{"x":[0.167],"y":[0]},"t":0,"s":[0]},{"i":{"x":[0.226],"y":[1]},"o":{"x":[0.194],"y":[0]},"t":11,"s":[0]},{"i":{"x":[0.226],"y":[1]},"o":{"x":[0.167],"y":[0]},"t":13,"s":[100]},{"i":{"x":[0.667],"y":[1]},"o":{"x":[0.167],"y":[0]},"t":36,"s":[100]},{"t":38,"s":[0]}],"ix":5},"r":1,"bm":0,"nm":"Fill 1","mn":"ADBE Vector Graphic - Fill","hd":false},{"ty":"st","c":{"a":0,"k":[1,1,1,1],"ix":3},"o":{"a":1,"k":[{"i":{"x":[0.667],"y":[1]},"o":{"x":[0.167],"y":[0]},"t":0,"s":[100]},{"i":{"x":[0.226],"y":[1]},"o":{"x":[0.194],"y":[0]},"t":11,"s":[100]},{"i":{"x":[0.226],"y":[1]},"o":{"x":[0.167],"y":[0]},"t":13,"s":[0]},{"i":{"x":[0.667],"y":[1]},"o":{"x":[0.167],"y":[0]},"t":36,"s":[0]},{"t":38,"s":[100]}],"ix":4},"w":{"a":0,"k":2,"ix":5},"lc":1,"lj":1,"ml":4,"bm":0,"nm":"Stroke 1","mn":"ADBE Vector Graphic - Stroke","hd":false}],"ip":0,"op":120,"st":0,"bm":0},{"ddd":0,"ind":2,"ty":4,"nm":"connect-male Outlines","sr":1,"ks":{"o":{"a":0,"k":100,"ix":11},"r":{"a":0,"k":0,"ix":10},"p":{"a":1,"k":[{"i":{"x":0.108,"y":1},"o":{"x":0.558,"y":0},"t":0,"s":[81.756,118.479,0],"to":[0.323,-0.323,0],"ti":[-0.844,0.844,0]},{"i":{"x":0.047,"y":1},"o":{"x":0.4,"y":0},"t":30,"s":[88.756,111.479,0],"to":[1.167,-1.167,0],"ti":[-1.167,1.167,0]},{"i":{"x":0.842,"y":0.848},"o":{"x":0.558,"y":0},"t":60,"s":[76.756,123.479,0],"to":[0.323,-0.323,0],"ti":[-0.71,0.71,0]},{"i":{"x":0.667,"y":1},"o":{"x":0.443,"y":0.773},"t":79.666,"s":[83.379,116.856,0],"to":[1.857,-1.857,0],"ti":[-1.167,1.167,0]},{"t":119,"s":[76.756,123.479,0]}],"ix":2},"a":{"a":0,"k":[25.718,25.599,0],"ix":1},"s":{"a":0,"k":[100,100,100],"ix":6}},"ao":0,"shapes":[{"ty":"gr","it":[{"ind":0,"ty":"sh","ix":1,"ks":{"a":0,"k":{"i":[[-3.559,-5.781],[0.051,-0.051],[0,0],[-1.367,-1.367],[-1.367,1.367],[0,0],[-0.047,0.053],[-5.01,5.01],[0,0],[0,0],[0,0],[1.367,1.367],[1.367,-1.366],[0,0],[0,0],[0,0],[1.366,1.367],[1.367,-1.367],[0,0],[0,0],[0,0]],"o":[[-0.053,0.047],[0,0],[-1.367,1.367],[1.367,1.367],[0,0],[0.051,-0.051],[5.78,3.559],[0,0],[0,0],[0,0],[1.367,-1.367],[-1.367,-1.366],[0,0],[0,0],[0,0],[1.366,-1.367],[-1.367,-1.367],[0,0],[0,0],[0,0],[-5.01,5.01]],"v":[[-14.039,9],[-14.202,9.133],[-24.101,19.032],[-24.101,23.982],[-19.151,23.982],[-9.252,14.083],[-9.119,13.92],[9.336,11.758],[21.003,0.091],[17.94,-2.972],[24.101,-9.133],[24.101,-14.083],[19.151,-14.083],[12.99,-7.922],[8.041,-12.871],[14.202,-19.032],[14.202,-23.982],[9.252,-23.982],[3.091,-17.821],[-0.21,-21.122],[-11.877,-9.455]],"c":true},"ix":2},"nm":"Path 1","mn":"ADBE Vector Shape - Group","hd":false},{"ty":"tr","p":{"a":0,"k":[25.718,25.599],"ix":2},"a":{"a":0,"k":[0,0],"ix":1},"s":{"a":0,"k":[100,100],"ix":3},"r":{"a":0,"k":0,"ix":6},"o":{"a":0,"k":100,"ix":7},"sk":{"a":0,"k":0,"ix":4},"sa":{"a":0,"k":0,"ix":5},"nm":"Transform"}],"nm":"Group 1","np":1,"cix":2,"bm":0,"ix":1,"mn":"ADBE Vector Group","hd":false},{"ty":"fl","c":{"a":0,"k":[1,1,1,1],"ix":4},"o":{"a":1,"k":[{"i":{"x":[0.667],"y":[1]},"o":{"x":[0.167],"y":[0]},"t":0,"s":[0]},{"i":{"x":[0.226],"y":[1]},"o":{"x":[0.194],"y":[0]},"t":11,"s":[0]},{"i":{"x":[0.226],"y":[1]},"o":{"x":[0.167],"y":[0]},"t":13,"s":[100]},{"i":{"x":[0.667],"y":[1]},"o":{"x":[0.167],"y":[0]},"t":36,"s":[100]},{"t":38,"s":[0]}],"ix":5},"r":1,"bm":0,"nm":"Fill 1","mn":"ADBE Vector Graphic - Fill","hd":false},{"ty":"st","c":{"a":0,"k":[1,1,1,1],"ix":3},"o":{"a":1,"k":[{"i":{"x":[0.667],"y":[1]},"o":{"x":[0.167],"y":[0]},"t":0,"s":[100]},{"i":{"x":[0.226],"y":[1]},"o":{"x":[0.194],"y":[0]},"t":11,"s":[100]},{"i":{"x":[0.226],"y":[1]},"o":{"x":[0.167],"y":[0]},"t":13,"s":[0]},{"i":{"x":[0.667],"y":[1]},"o":{"x":[0.167],"y":[0]},"t":36,"s":[0]},{"t":38,"s":[100]}],"ix":4},"w":{"a":0,"k":2,"ix":5},"lc":1,"lj":1,"ml":4,"bm":0,"nm":"Stroke 1","mn":"ADBE Vector Graphic - Stroke","hd":false}],"ip":0,"op":120,"st":0,"bm":0}],"markers":[]}