{"v":"5.4.4","fr":24,"ip":0,"op":28,"w":48,"h":48,"nm":"facebook-circled-click","ddd":0,"assets":[],"layers":[{"ddd":0,"ind":1,"ty":4,"nm":"Circle mask","td":1,"sr":1,"ks":{"o":{"a":0,"k":100,"ix":11},"r":{"a":0,"k":0,"ix":10},"p":{"a":0,"k":[24,24,0],"ix":2},"a":{"a":0,"k":[24,24,0],"ix":1},"s":{"a":0,"k":[100,100,100],"ix":6}},"ao":0,"shapes":[{"ty":"gr","it":[{"ind":0,"ty":"sh","ix":1,"ks":{"a":0,"k":{"i":[[10.493,0],[0,-10.494],[-10.494,0],[0,10.493]],"o":[[-10.494,0],[0,10.493],[10.493,0],[0,-10.494]],"v":[[0,-19],[-19,0],[0,19],[19,0]],"c":true},"ix":2},"nm":"Path 1","mn":"ADBE Vector Shape - Group","hd":false},{"ty":"fl","c":{"a":0,"k":[0.011999999776,0.607999973671,0.898000021542,1],"ix":4},"o":{"a":0,"k":100,"ix":5},"r":1,"bm":0,"nm":"Fill 1","mn":"ADBE Vector Graphic - Fill","hd":false},{"ty":"tr","p":{"a":0,"k":[24,24],"ix":2},"a":{"a":0,"k":[0,0],"ix":1},"s":{"a":0,"k":[100,100],"ix":3},"r":{"a":0,"k":0,"ix":6},"o":{"a":0,"k":100,"ix":7},"sk":{"a":0,"k":0,"ix":4},"sa":{"a":0,"k":0,"ix":5},"nm":"Transform"}],"nm":"Group 2","np":2,"cix":2,"bm":0,"ix":1,"mn":"ADBE Vector Group","hd":false}],"ip":0,"op":28,"st":0,"bm":0},{"ddd":0,"ind":2,"ty":4,"nm":"F","tt":1,"sr":1,"ks":{"o":{"a":0,"k":100,"ix":11},"r":{"a":1,"k":[{"i":{"x":[0.833],"y":[0.833]},"o":{"x":[0.167],"y":[0.167]},"t":0,"s":[0],"e":[90]},{"i":{"x":[0.679],"y":[1]},"o":{"x":[0.167],"y":[0.167]},"t":5,"s":[90],"e":[0]},{"t":21}],"ix":10},"p":{"a":0,"k":[24,24,0],"ix":2},"a":{"a":0,"k":[24,24,0],"ix":1},"s":{"a":1,"k":[{"i":{"x":[0.833,0.833,0.833],"y":[0.833,0.833,0.833]},"o":{"x":[0.167,0.167,0.167],"y":[0.167,0.167,0.167]},"t":0,"s":[100,100,100],"e":[10,10,100]},{"i":{"x":[0.667,0.667,0.667],"y":[1,1,1]},"o":{"x":[0.167,0.167,0.167],"y":[0.167,0.167,0]},"t":3,"s":[10,10,100],"e":[100,100,100]},{"t":23}],"ix":6}},"ao":0,"shapes":[{"ty":"gr","it":[{"ind":0,"ty":"sh","ix":1,"ks":{"a":0,"k":{"i":[[0,0],[0,0],[0,0],[0,0],[0,0],[-1.941,0],[0,0],[0,0],[2.189,0],[0,-5.502],[0,0],[0,0],[0,0],[0,0],[0,0],[-0.968,0],[-0.844,0.114]],"o":[[0,0],[0,0],[0,0],[0,0],[0,-2.075],[0,0],[0,0],[-0.548,-0.074],[-4.573,0],[0,0],[0,0],[0,0],[0,0],[0,0],[0.931,0.14],[0.875,0],[0,0]],"v":[[2.189,-0.365],[7.107,-0.365],[7.878,-5.359],[2.188,-5.359],[2.188,-8.089],[4.807,-12.005],[7.926,-12.005],[7.926,-16.363],[4.029,-16.6],[-3.225,-8.682],[-3.225,-5.359],[-7.926,-5.359],[-7.926,-0.365],[-3.225,-0.365],[-3.225,16.365],[-0.383,16.6],[2.189,16.406]],"c":true},"ix":2},"nm":"Path 1","mn":"ADBE Vector Shape - Group","hd":false},{"ty":"fl","c":{"a":0,"k":[1,1,1,1],"ix":4},"o":{"a":0,"k":100,"ix":5},"r":1,"bm":0,"nm":"Fill 1","mn":"ADBE Vector Graphic - Fill","hd":false},{"ty":"tr","p":{"a":0,"k":[24.383,29.401],"ix":2},"a":{"a":0,"k":[0,0],"ix":1},"s":{"a":0,"k":[100,100],"ix":3},"r":{"a":0,"k":0,"ix":6},"o":{"a":0,"k":100,"ix":7},"sk":{"a":0,"k":0,"ix":4},"sa":{"a":0,"k":0,"ix":5},"nm":"Transform"}],"nm":"Group 1","np":2,"cix":2,"bm":0,"ix":1,"mn":"ADBE Vector Group","hd":false}],"ip":0,"op":28,"st":0,"bm":0},{"ddd":0,"ind":3,"ty":4,"nm":"Circle","sr":1,"ks":{"o":{"a":0,"k":100,"ix":11},"r":{"a":0,"k":0,"ix":10},"p":{"a":0,"k":[24,24,0],"ix":2},"a":{"a":0,"k":[24,24,0],"ix":1},"s":{"a":0,"k":[100,100,100],"ix":6}},"ao":0,"shapes":[{"ty":"gr","it":[{"ind":0,"ty":"sh","ix":1,"ks":{"a":0,"k":{"i":[[10.493,0],[0,-10.494],[-10.494,0],[0,10.493]],"o":[[-10.494,0],[0,10.493],[10.493,0],[0,-10.494]],"v":[[0,-19],[-19,0],[0,19],[19,0]],"c":true},"ix":2},"nm":"Path 1","mn":"ADBE Vector Shape - Group","hd":false},{"ty":"fl","c":{"a":0,"k":[0.011999999776,0.607999973671,0.898000021542,1],"ix":4},"o":{"a":0,"k":100,"ix":5},"r":1,"bm":0,"nm":"Fill 1","mn":"ADBE Vector Graphic - Fill","hd":false},{"ty":"tr","p":{"a":0,"k":[24,24],"ix":2},"a":{"a":0,"k":[0,0],"ix":1},"s":{"a":0,"k":[100,100],"ix":3},"r":{"a":0,"k":0,"ix":6},"o":{"a":0,"k":100,"ix":7},"sk":{"a":0,"k":0,"ix":4},"sa":{"a":0,"k":0,"ix":5},"nm":"Transform"}],"nm":"Group 2","np":2,"cix":2,"bm":0,"ix":1,"mn":"ADBE Vector Group","hd":false}],"ip":0,"op":28,"st":0,"bm":0}],"markers":[]}